[
  {
    "message": "Sohom pushed to \"dev\" on 3rd July 2025 - 11:00 AM UTC",
    "timestamp": { "$date": "2025-07-03T11:00:00Z" }
  },
  {
    "message": "Sohom submitted a pull request from \"feature/login\" to \"dev\" on 3rd July 2025 - 11:30 AM UTC",
    "timestamp": { "$date": "2025-07-03T11:30:00Z" }
  },
  {
    "message": "Sohom merged branch \"feature/login\" to \"dev\" on 3rd July 2025 - 12:00 PM UTC",
    "timestamp": { "$date": "2025-07-03T12:00:00Z" }
  },
  {
    "message": "Piuli pushed to \"staging\" on 3rd July 2025 - 01:15 PM UTC",
    "timestamp": { "$date": "2025-07-03T13:15:00Z" }
  },
  {
    "message": "Piuli submitted a pull request from \"staging\" to \"master\" on 3rd July 2025 - 02:00 PM UTC",
    "timestamp": { "$date": "2025-07-03T14:00:00Z" }
  }
]
